{
  "name": "Atlético de Madrid",
  "type": "club",
  "players": [
    {
      "name": "J. Oblak",
      "number": 1,
      "position": "GK",
      "overall": 91,
      "attributes": {
        "pace": 87,
        "defending": 90,
        "passing": 92,
        "dribbling": 90,
        "physicality": 78,
        "stamina": 41,
        "awareness": 88,
        "composure": 68
      }
    },
    {
      "name": "L. Suárez",
      "number": 2,
      "position": "CM",
      "overall": 88,
      "attributes": {
        "pace": 69,
        "shooting": 93,
        "passing": 83,
        "dribbling": 83,
        "defending": 45,
        "physicality": 85,
        "stamina": 78,
        "awareness": 92,
        "composure": 87
      }
    },
    {
      "name": "Marcos Llorente",
      "number": 3,
      "position": "RW",
      "overall": 86,
      "attributes": {
        "pace": 90,
        "shooting": 81,
        "passing": 86,
        "dribbling": 82,
        "defending": 80,
        "physicality": 79,
        "stamina": 90,
        "awareness": 86,
        "composure": 83
      }
    },
    {
      "name": "A. Griezmann",
      "number": 4,
      "position": "CM",
      "overall": 85,
      "attributes": {
        "pace": 80,
        "shooting": 84,
        "passing": 84,
        "dribbling": 85,
        "defending": 54,
        "physicality": 63,
        "stamina": 86,
        "awareness": 89,
        "composure": 90
      }
    },
    {
      "name": "Koke",
      "number": 5,
      "position": "CM",
      "overall": 85,
      "attributes": {
        "pace": 69,
        "shooting": 72,
        "passing": 86,
        "dribbling": 80,
        "defending": 81,
        "physicality": 75,
        "stamina": 93,
        "awareness": 88,
        "composure": 86
      }
    },
    {
      "name": "19 Filipe Luís",
      "number": 6,
      "position": "LB",
      "overall": 85,
      "attributes": {
        "pace": 75,
        "shooting": 59,
        "passing": 80,
        "dribbling": 77,
        "defending": 84,
        "physicality": 73,
        "stamina": 89,
        "awareness": 85,
        "composure": 88
      }
    },
    {
      "name": "K. Trippier",
      "number": 7,
      "position": "CM",
      "overall": 84,
      "attributes": {
        "pace": 73,
        "shooting": 54,
        "passing": 81,
        "dribbling": 74,
        "defending": 81,
        "physicality": 64,
        "stamina": 87,
        "awareness": 81,
        "composure": 77
      }
    },
    {
      "name": "Y. Carrasco",
      "number": 8,
      "position": "LW",
      "overall": 84,
      "attributes": {
        "pace": 88,
        "shooting": 81,
        "passing": 79,
        "dribbling": 88,
        "defending": 47,
        "physicality": 61,
        "stamina": 80,
        "awareness": 80,
        "composure": 79
      }
    },
    {
      "name": "Felipe",
      "number": 9,
      "position": "CM",
      "overall": 84,
      "attributes": {
        "pace": 66,
        "shooting": 39,
        "passing": 73,
        "dribbling": 57,
        "defending": 85,
        "physicality": 90,
        "stamina": 68,
        "awareness": 81,
        "composure": 75
      }
    },
    {
      "name": "J. Giménez",
      "number": 10,
      "position": "CB",
      "overall": 84,
      "attributes": {
        "pace": 73,
        "shooting": 37,
        "passing": 70,
        "dribbling": 54,
        "defending": 87,
        "physicality": 86,
        "stamina": 60,
        "awareness": 78,
        "composure": 76
      }
    },
    {
      "name": "S. Savić",
      "number": 11,
      "position": "CB",
      "overall": 84,
      "attributes": {
        "pace": 67,
        "shooting": 34,
        "passing": 73,
        "dribbling": 47,
        "defending": 86,
        "physicality": 83,
        "stamina": 53,
        "awareness": 83,
        "composure": 80
      }
    },
    {
      "name": "T. Lemar",
      "number": 12,
      "position": "CM",
      "overall": 83,
      "attributes": {
        "pace": 80,
        "shooting": 75,
        "passing": 83,
        "dribbling": 88,
        "defending": 59,
        "physicality": 55,
        "stamina": 76,
        "awareness": 81,
        "composure": 79
      }
    },
    {
      "name": "A. Correa",
      "number": 13,
      "position": "CM",
      "overall": 83,
      "attributes": {
        "pace": 85,
        "shooting": 85,
        "passing": 82,
        "dribbling": 88,
        "defending": 53,
        "physicality": 71,
        "stamina": 82,
        "awareness": 84,
        "composure": 76
      }
    },
    {
      "name": "João Félix",
      "number": 14,
      "position": "CM",
      "overall": 83,
      "attributes": {
        "pace": 83,
        "shooting": 79,
        "passing": 80,
        "dribbling": 86,
        "defending": 42,
        "physicality": 64,
        "stamina": 75,
        "awareness": 83,
        "composure": 84
      }
    },
    {
      "name": "R. De Paul",
      "number": 15,
      "position": "CM",
      "overall": 82,
      "attributes": {
        "pace": 76,
        "shooting": 76,
        "passing": 85,
        "dribbling": 81,
        "defending": 79,
        "physicality": 81,
        "stamina": 86,
        "awareness": 81,
        "composure": 80
      }
    },
    {
      "name": "Mario Hermoso",
      "number": 16,
      "position": "CB",
      "overall": 82,
      "attributes": {
        "pace": 79,
        "shooting": 42,
        "passing": 78,
        "dribbling": 66,
        "defending": 84,
        "physicality": 81,
        "stamina": 77,
        "awareness": 82,
        "composure": 79
      }
    },
    {
      "name": "Renan Lodi",
      "number": 17,
      "position": "CM",
      "overall": 81,
      "attributes": {
        "pace": 83,
        "shooting": 64,
        "passing": 77,
        "dribbling": 81,
        "defending": 78,
        "physicality": 70,
        "stamina": 84,
        "awareness": 80,
        "composure": 79
      }
    },
    {
      "name": "H. Herrera",
      "number": 18,
      "position": "CM",
      "overall": 81,
      "attributes": {
        "pace": 70,
        "shooting": 72,
        "passing": 81,
        "dribbling": 76,
        "defending": 82,
        "physicality": 80,
        "stamina": 93,
        "awareness": 81,
        "composure": 77
      }
    },
    {
      "name": "18 Gabi",
      "number": 19,
      "position": "CM",
      "overall": 81,
      "attributes": {
        "pace": 65,
        "shooting": 67,
        "passing": 84,
        "dribbling": 74,
        "defending": 79,
        "physicality": 69,
        "stamina": 76,
        "awareness": 80,
        "composure": 83
      }
    },
    {
      "name": "17 Tiago",
      "number": 20,
      "position": "CM",
      "overall": 81,
      "attributes": {
        "pace": 55,
        "shooting": 62,
        "passing": 84,
        "dribbling": 70,
        "defending": 77,
        "physicality": 76,
        "stamina": 67,
        "awareness": 77,
        "composure": 78
      }
    },
    {
      "name": "19 Juanfran",
      "number": 21,
      "position": "RB",
      "overall": 80,
      "attributes": {
        "pace": 83,
        "shooting": 54,
        "passing": 77,
        "dribbling": 75,
        "defending": 81,
        "physicality": 74,
        "stamina": 80,
        "awareness": 82,
        "composure": 74
      }
    },
    {
      "name": "S. Vrsaljko",
      "number": 22,
      "position": "CM",
      "overall": 80,
      "attributes": {
        "pace": 81,
        "shooting": 44,
        "passing": 76,
        "dribbling": 74,
        "defending": 80,
        "physicality": 73,
        "stamina": 85,
        "awareness": 74,
        "composure": 67
      }
    },
    {
      "name": "21 Diego Costa",
      "number": 23,
      "position": "CM",
      "overall": 80,
      "attributes": {
        "pace": 75,
        "shooting": 82,
        "passing": 65,
        "dribbling": 75,
        "defending": 39,
        "physicality": 92,
        "stamina": 73,
        "awareness": 80,
        "composure": 83
      }
    }
  ]
}