{
  "name": "FC Schalke 04",
  "type": "club",
  "logo": "https://cdn.sofifa.net/meta/team/67/30.png",
  "players": [
    {
      "name": "Kenan Karaman -",
      "number": 1,
      "position": "CAM",
      "overall": 73,
      "attributes": {
        "pace": 70,
        "shooting": 70,
        "passing": 70,
        "dribbling": 70,
        "defending": 70,
        "physicality": 70,
        "stamina": 70,
        "awareness": 70,
        "composure": 70
      },
      "image": "https://cdn.sofifa.net/players/212/240/25_120.png"
    },
    {
      "name": "Moussa Sylla -",
      "number": 2,
      "position": "ST",
      "overall": 73,
      "attributes": {
        "pace": 70,
        "shooting": 70,
        "passing": 70,
        "dribbling": 70,
        "defending": 70,
        "physicality": 70,
        "stamina": 70,
        "awareness": 70,
        "composure": 70
      },
      "image": "https://cdn.sofifa.net/players/237/708/25_120.png"
    },
    {
      "name": "Paul Seguin -",
      "number": 3,
      "position": "CDM",
      "overall": 72,
      "attributes": {
        "pace": 70,
        "shooting": 70,
        "passing": 70,
        "dribbling": 70,
        "defending": 70,
        "physicality": 70,
        "stamina": 70,
        "awareness": 70,
        "composure": 70
      },
      "image": "https://cdn.sofifa.net/players/221/885/25_120.png"
    },
    {
      "name": "Pape Meïssa Ba -",
      "number": 4,
      "position": "ST",
      "overall": 70,
      "attributes": {
        "pace": 70,
        "shooting": 70,
        "passing": 70,
        "dribbling": 70,
        "defending": 70,
        "physicality": 70,
        "stamina": 70,
        "awareness": 70,
        "composure": 70
      },
      "image": "https://cdn.sofifa.net/players/254/501/25_120.png"
    },
    {
      "name": "Amin Younes -",
      "number": 5,
      "position": "CAM",
      "overall": 70,
      "attributes": {
        "pace": 70,
        "shooting": 70,
        "passing": 70,
        "dribbling": 70,
        "defending": 70,
        "physicality": 70,
        "stamina": 70,
        "awareness": 70,
        "composure": 70
      },
      "image": "https://cdn.sofifa.net/players/205/966/25_120.png"
    },
    {
      "name": "Christopher Antwi-Adjei -",
      "number": 6,
      "position": "LW",
      "overall": 70,
      "attributes": {
        "pace": 70,
        "shooting": 70,
        "passing": 70,
        "dribbling": 70,
        "defending": 70,
        "physicality": 70,
        "stamina": 70,
        "awareness": 70,
        "composure": 70
      },
      "image": "https://cdn.sofifa.net/players/239/073/25_120.png"
    },
    {
      "name": "Loris Sven Karius -",
      "number": 7,
      "position": "GK",
      "overall": 70,
      "attributes": {
        "pace": 70,
        "defending": 70,
        "passing": 70,
        "dribbling": 70,
        "physicality": 70,
        "stamina": 70,
        "awareness": 70,
        "composure": 70
      },
      "image": "https://cdn.sofifa.net/players/203/775/25_120.png"
    },
    {
      "name": "Aymen Barkok -",
      "number": 8,
      "position": "CAM",
      "overall": 69,
      "attributes": {
        "pace": 70,
        "shooting": 70,
        "passing": 70,
        "dribbling": 70,
        "defending": 70,
        "physicality": 70,
        "stamina": 70,
        "awareness": 70,
        "composure": 70
      },
      "image": "https://cdn.sofifa.net/players/236/624/25_120.png"
    },
    {
      "name": "Tomáš Kalas -",
      "number": 9,
      "position": "CB",
      "overall": 69,
      "attributes": {
        "pace": 70,
        "shooting": 70,
        "passing": 70,
        "dribbling": 70,
        "defending": 70,
        "physicality": 70,
        "stamina": 70,
        "awareness": 70,
        "composure": 70
      },
      "image": "https://cdn.sofifa.net/players/201/122/25_120.png"
    },
    {
      "name": "Tobias Mohr -",
      "number": 10,
      "position": "LW",
      "overall": 69,
      "attributes": {
        "pace": 70,
        "shooting": 70,
        "passing": 70,
        "dribbling": 70,
        "defending": 70,
        "physicality": 70,
        "stamina": 70,
        "awareness": 70,
        "composure": 70
      },
      "image": "https://cdn.sofifa.net/players/243/887/25_120.png"
    },
    {
      "name": "Derry John Murkin -",
      "number": 11,
      "position": "LB",
      "overall": 69,
      "attributes": {
        "pace": 70,
        "shooting": 70,
        "passing": 70,
        "dribbling": 70,
        "defending": 70,
        "physicality": 70,
        "stamina": 70,
        "awareness": 70,
        "composure": 70
      },
      "image": "https://cdn.sofifa.net/players/269/248/25_120.png"
    },
    {
      "name": "Ron Schallenberg -",
      "number": 12,
      "position": "CDM",
      "overall": 69,
      "attributes": {
        "pace": 70,
        "shooting": 70,
        "passing": 70,
        "dribbling": 70,
        "defending": 70,
        "physicality": 70,
        "stamina": 70,
        "awareness": 70,
        "composure": 70
      },
      "image": "https://cdn.sofifa.net/players/239/099/25_120.png"
    },
    {
      "name": "Marcin Kamiński -",
      "number": 13,
      "position": "CB",
      "overall": 68,
      "attributes": {
        "pace": 70,
        "shooting": 70,
        "passing": 70,
        "dribbling": 70,
        "defending": 70,
        "physicality": 70,
        "stamina": 70,
        "awareness": 70,
        "composure": 70
      },
      "image": "https://cdn.sofifa.net/players/199/761/25_120.png"
    },
    {
      "name": "Mehmet Can Aydın -",
      "number": 14,
      "position": "RB",
      "overall": 67,
      "attributes": {
        "pace": 70,
        "shooting": 70,
        "passing": 70,
        "dribbling": 70,
        "defending": 70,
        "physicality": 70,
        "stamina": 70,
        "awareness": 70,
        "composure": 70
      },
      "image": "https://cdn.sofifa.net/players/261/446/25_120.png"
    },
    {
      "name": "Ralf Sebastian Fährmann -",
      "number": 15,
      "position": "GK",
      "overall": 67,
      "attributes": {
        "pace": 70,
        "defending": 70,
        "passing": 70,
        "dribbling": 70,
        "physicality": 70,
        "stamina": 70,
        "awareness": 70,
        "composure": 70
      },
      "image": "https://cdn.sofifa.net/players/179/783/25_120.png"
    },
    {
      "name": "Janik Jay Bachmann -",
      "number": 16,
      "position": "CDM",
      "overall": 67,
      "attributes": {
        "pace": 70,
        "shooting": 70,
        "passing": 70,
        "dribbling": 70,
        "defending": 70,
        "physicality": 70,
        "stamina": 70,
        "awareness": 70,
        "composure": 70
      },
      "image": "https://cdn.sofifa.net/players/224/094/25_120.png"
    },
    {
      "name": "Dominick Drexler -",
      "number": 17,
      "position": "CAM",
      "overall": 67,
      "attributes": {
        "pace": 70,
        "shooting": 70,
        "passing": 70,
        "dribbling": 70,
        "defending": 70,
        "physicality": 70,
        "stamina": 70,
        "awareness": 70,
        "composure": 70
      },
      "image": "https://cdn.sofifa.net/players/198/617/25_120.png"
    },
    {
      "name": "Felipe Sánchez -",
      "number": 18,
      "position": "CB",
      "overall": 67,
      "attributes": {
        "pace": 70,
        "shooting": 70,
        "passing": 70,
        "dribbling": 70,
        "defending": 70,
        "physicality": 70,
        "stamina": 70,
        "awareness": 70,
        "composure": 70
      },
      "image": "https://cdn.sofifa.net/players/273/904/25_120.png"
    },
    {
      "name": "Anton-Leander Donkor -",
      "number": 19,
      "position": "LB",
      "overall": 66,
      "attributes": {
        "pace": 70,
        "shooting": 70,
        "passing": 70,
        "dribbling": 70,
        "defending": 70,
        "physicality": 70,
        "stamina": 70,
        "awareness": 70,
        "composure": 70
      },
      "image": "https://cdn.sofifa.net/players/232/203/25_120.png"
    },
    {
      "name": "Taylan Bulut -",
      "number": 20,
      "position": "RB",
      "overall": 66,
      "attributes": {
        "pace": 70,
        "shooting": 70,
        "passing": 70,
        "dribbling": 70,
        "defending": 70,
        "physicality": 70,
        "stamina": 70,
        "awareness": 70,
        "composure": 70
      },
      "image": "https://cdn.sofifa.net/players/072/315/25_120.png"
    },
    {
      "name": "Justin Heekeren -",
      "number": 21,
      "position": "GK",
      "overall": 66,
      "attributes": {
        "pace": 70,
        "defending": 70,
        "passing": 70,
        "dribbling": 70,
        "physicality": 70,
        "stamina": 70,
        "awareness": 70,
        "composure": 70
      },
      "image": "https://cdn.sofifa.net/players/269/955/25_120.png"
    },
    {
      "name": "Ilyes Hamache -",
      "number": 22,
      "position": "LW",
      "overall": 65,
      "attributes": {
        "pace": 70,
        "shooting": 70,
        "passing": 70,
        "dribbling": 70,
        "defending": 70,
        "physicality": 70,
        "stamina": 70,
        "awareness": 70,
        "composure": 70
      },
      "image": "https://cdn.sofifa.net/players/264/501/25_120.png"
    },
    {
      "name": "Michael Langer -",
      "number": 23,
      "position": "GK",
      "overall": 65,
      "attributes": {
        "pace": 70,
        "defending": 70,
        "passing": 70,
        "dribbling": 70,
        "physicality": 70,
        "stamina": 70,
        "awareness": 70,
        "composure": 70
      },
      "image": "https://cdn.sofifa.net/players/107/084/25_120.png"
    }
  ]
}