{
  "name": "Hertha BSC",
  "type": "club",
  "players": [
    {
      "name": "21 S. Khedira",
      "number": 1,
      "position": "CM",
      "overall": 81,
      "attributes": {
        "pace": 49,
        "shooting": 68,
        "passing": 82,
        "dribbling": 78,
        "defending": 80,
        "physicality": 85,
        "stamina": 65,
        "awareness": 79,
        "composure": 84
      }
    },
    {
      "name": "K. Boateng",
      "number": 2,
      "position": "CM",
      "overall": 78,
      "attributes": {
        "pace": 72,
        "shooting": 76,
        "passing": 80,
        "dribbling": 80,
        "defending": 73,
        "physicality": 80,
        "stamina": 54,
        "awareness": 72,
        "composure": 82
      }
    },
    {
      "name": "D. Boyata",
      "number": 3,
      "position": "CB",
      "overall": 78,
      "attributes": {
        "pace": 72,
        "shooting": 20,
        "passing": 72,
        "dribbling": 53,
        "defending": 81,
        "physicality": 88,
        "stamina": 73,
        "awareness": 64,
        "composure": 66
      }
    },
    {
      "name": "21 J. Córdoba",
      "number": 4,
      "position": "ST",
      "overall": 77,
      "attributes": {
        "pace": 78,
        "shooting": 78,
        "passing": 67,
        "dribbling": 75,
        "defending": 39,
        "physicality": 90,
        "stamina": 74,
        "awareness": 79,
        "composure": 76
      }
    },
    {
      "name": "S. Jovetić",
      "number": 5,
      "position": "CM",
      "overall": 77,
      "attributes": {
        "pace": 65,
        "shooting": 77,
        "passing": 80,
        "dribbling": 79,
        "defending": 32,
        "physicality": 70,
        "stamina": 45,
        "awareness": 77,
        "composure": 78
      }
    },
    {
      "name": "A. Schwolow",
      "number": 6,
      "position": "GK",
      "overall": 77,
      "attributes": {
        "pace": 76,
        "defending": 80,
        "passing": 75,
        "dribbling": 76,
        "physicality": 67,
        "stamina": 31,
        "awareness": 79,
        "composure": 34
      }
    },
    {
      "name": "V. Darida",
      "number": 7,
      "position": "CM",
      "overall": 76,
      "attributes": {
        "pace": 64,
        "shooting": 67,
        "passing": 76,
        "dribbling": 78,
        "defending": 74,
        "physicality": 48,
        "stamina": 95,
        "awareness": 75,
        "composure": 79
      }
    },
    {
      "name": "S. Serdar",
      "number": 8,
      "position": "RW",
      "overall": 76,
      "attributes": {
        "pace": 69,
        "shooting": 68,
        "passing": 75,
        "dribbling": 80,
        "defending": 75,
        "physicality": 76,
        "stamina": 80,
        "awareness": 77,
        "composure": 70
      }
    },
    {
      "name": "L. Tousart",
      "number": 9,
      "position": "CM",
      "overall": 76,
      "attributes": {
        "pace": 65,
        "shooting": 42,
        "passing": 76,
        "dribbling": 64,
        "defending": 78,
        "physicality": 81,
        "stamina": 85,
        "awareness": 71,
        "composure": 68
      }
    },
    {
      "name": "20 S. Kalou",
      "number": 10,
      "position": "CM",
      "overall": 76,
      "attributes": {
        "pace": 59,
        "shooting": 77,
        "passing": 76,
        "dribbling": 85,
        "defending": 35,
        "physicality": 66,
        "stamina": 60,
        "awareness": 80,
        "composure": 84
      }
    },
    {
      "name": "N. Stark",
      "number": 11,
      "position": "CB",
      "overall": 76,
      "attributes": {
        "pace": 78,
        "shooting": 48,
        "passing": 74,
        "dribbling": 70,
        "defending": 77,
        "physicality": 79,
        "stamina": 73,
        "awareness": 73,
        "composure": 68
      }
    },
    {
      "name": "K. Piątek",
      "number": 12,
      "position": "CM",
      "overall": 76,
      "attributes": {
        "pace": 78,
        "shooting": 81,
        "passing": 64,
        "dribbling": 70,
        "defending": 34,
        "physicality": 76,
        "stamina": 72,
        "awareness": 75,
        "composure": 75
      }
    },
    {
      "name": "R. Jarstein",
      "number": 13,
      "position": "CM",
      "overall": 76,
      "attributes": {
        "pace": 40,
        "shooting": 13,
        "passing": 29,
        "dribbling": 17,
        "defending": 11,
        "physicality": 70,
        "stamina": 30,
        "awareness": 70,
        "composure": 50
      }
    },
    {
      "name": "20 T. Kraft",
      "number": 14,
      "position": "CM",
      "overall": 75,
      "attributes": {
        "pace": 50,
        "shooting": 14,
        "passing": 35,
        "dribbling": 13,
        "defending": 19,
        "physicality": 68,
        "stamina": 35,
        "awareness": 74,
        "composure": 45
      }
    },
    {
      "name": "M. Plattenhardt",
      "number": 15,
      "position": "LW",
      "overall": 74,
      "attributes": {
        "pace": 71,
        "shooting": 43,
        "passing": 74,
        "dribbling": 71,
        "defending": 75,
        "physicality": 73,
        "stamina": 71,
        "awareness": 72,
        "composure": 67
      }
    },
    {
      "name": "M. Mittelstädt",
      "number": 16,
      "position": "CM",
      "overall": 74,
      "attributes": {
        "pace": 81,
        "shooting": 59,
        "passing": 70,
        "dribbling": 74,
        "defending": 74,
        "physicality": 63,
        "stamina": 73,
        "awareness": 70,
        "composure": 60
      }
    },
    {
      "name": "I. Belfodil",
      "number": 17,
      "position": "ST",
      "overall": 74,
      "attributes": {
        "pace": 65,
        "shooting": 75,
        "passing": 72,
        "dribbling": 77,
        "defending": 39,
        "physicality": 77,
        "stamina": 63,
        "awareness": 71,
        "composure": 71
      }
    },
    {
      "name": "D. Zeefuik",
      "number": 18,
      "position": "RW",
      "overall": 74,
      "attributes": {
        "pace": 87,
        "shooting": 33,
        "passing": 64,
        "dribbling": 71,
        "defending": 74,
        "physicality": 77,
        "stamina": 80,
        "awareness": 68,
        "composure": 67
      }
    },
    {
      "name": "S. Ascacíbar",
      "number": 19,
      "position": "CM",
      "overall": 74,
      "attributes": {
        "pace": 54,
        "shooting": 39,
        "passing": 69,
        "dribbling": 65,
        "defending": 78,
        "physicality": 57,
        "stamina": 84,
        "awareness": 73,
        "composure": 67
      }
    },
    {
      "name": "P. Pekarík",
      "number": 20,
      "position": "CM",
      "overall": 74,
      "attributes": {
        "pace": 60,
        "shooting": 35,
        "passing": 70,
        "dribbling": 73,
        "defending": 76,
        "physicality": 62,
        "stamina": 79,
        "awareness": 73,
        "composure": 73
      }
    },
    {
      "name": "M. Richter",
      "number": 21,
      "position": "CM",
      "overall": 74,
      "attributes": {
        "pace": 68,
        "shooting": 70,
        "passing": 69,
        "dribbling": 78,
        "defending": 25,
        "physicality": 63,
        "stamina": 71,
        "awareness": 75,
        "composure": 62
      }
    },
    {
      "name": "J. Torunarigha",
      "number": 22,
      "position": "CM",
      "overall": 73,
      "attributes": {
        "pace": 75,
        "shooting": 33,
        "passing": 69,
        "dribbling": 67,
        "defending": 76,
        "physicality": 78,
        "stamina": 70,
        "awareness": 61,
        "composure": 70
      }
    },
    {
      "name": "D. Selke",
      "number": 23,
      "position": "CM",
      "overall": 71,
      "attributes": {
        "pace": 81,
        "shooting": 70,
        "passing": 64,
        "dribbling": 69,
        "defending": 39,
        "physicality": 77,
        "stamina": 66,
        "awareness": 71,
        "composure": 64
      }
    }
  ]
}