{
  "name": "Montpellier HSC",
  "type": "club",
  "logo": "https://cdn.sofifa.net/meta/team/581/30.png",
  "players": [
    {
      "name": "Benjamin Lecomte -",
      "number": 40,
      "position": "GK",
      "overall": 75,
      "attributes": {
        "pace": 70,
        "defending": 70,
        "passing": 70,
        "dribbling": 70,
        "physicality": 70,
        "stamina": 70,
        "awareness": 70,
        "composure": 70
      },
      "image": "https://cdn.sofifa.net/players/200/726/25_120.png"
    },
    {
      "name": "Bećir Omeragić -",
      "number": 27,
      "position": "CB",
      "overall": 75,
      "attributes": {
        "pace": 70,
        "shooting": 70,
        "passing": 70,
        "dribbling": 70,
        "defending": 70,
        "physicality": 70,
        "stamina": 70,
        "awareness": 70,
        "composure": 70
      },
      "image": "https://cdn.sofifa.net/players/244/603/25_120.png"
    },
    {
      "name": "Joris Chotard -",
      "number": 13,
      "position": "CDM",
      "overall": 75,
      "attributes": {
        "pace": 70,
        "shooting": 70,
        "passing": 70,
        "dribbling": 70,
        "defending": 70,
        "physicality": 70,
        "stamina": 70,
        "awareness": 70,
        "composure": 70
      },
      "image": "https://cdn.sofifa.net/players/252/541/25_120.png"
    },
    {
      "name": "Jordan Ferri -",
      "number": 12,
      "position": "CDM",
      "overall": 75,
      "attributes": {
        "pace": 70,
        "shooting": 70,
        "passing": 70,
        "dribbling": 70,
        "defending": 70,
        "physicality": 70,
        "stamina": 70,
        "awareness": 70,
        "composure": 70
      },
      "image": "https://cdn.sofifa.net/players/206/306/25_120.png"
    },
    {
      "name": "Dimitry Bertaud -",
      "number": 16,
      "position": "GK",
      "overall": 73,
      "attributes": {
        "pace": 70,
        "defending": 70,
        "passing": 70,
        "dribbling": 70,
        "physicality": 70,
        "stamina": 70,
        "awareness": 70,
        "composure": 70
      },
      "image": "https://cdn.sofifa.net/players/228/616/25_120.png"
    },
    {
      "name": "Modibo Sagnan -",
      "number": 5,
      "position": "CB",
      "overall": 73,
      "attributes": {
        "pace": 70,
        "shooting": 70,
        "passing": 70,
        "dribbling": 70,
        "defending": 70,
        "physicality": 70,
        "stamina": 70,
        "awareness": 70,
        "composure": 70
      },
      "image": "https://cdn.sofifa.net/players/241/708/25_120.png"
    },
    {
      "name": "Andy Delort -",
      "number": 9,
      "position": "ST",
      "overall": 73,
      "attributes": {
        "pace": 70,
        "shooting": 70,
        "passing": 70,
        "dribbling": 70,
        "defending": 70,
        "physicality": 70,
        "stamina": 70,
        "awareness": 70,
        "composure": 70
      },
      "image": "https://cdn.sofifa.net/players/193/983/25_120.png"
    },
    {
      "name": "Bamo Abdoul Meïté -",
      "number": 2,
      "position": "CB",
      "overall": 73,
      "attributes": {
        "pace": 70,
        "shooting": 70,
        "passing": 70,
        "dribbling": 70,
        "defending": 70,
        "physicality": 70,
        "stamina": 70,
        "awareness": 70,
        "composure": 70
      },
      "image": "https://cdn.sofifa.net/players/264/401/25_120.png"
    },
    {
      "name": "Boubakar Kouyaté -",
      "number": 4,
      "position": "CB",
      "overall": 73,
      "attributes": {
        "pace": 70,
        "shooting": 70,
        "passing": 70,
        "dribbling": 70,
        "defending": 70,
        "physicality": 70,
        "stamina": 70,
        "awareness": 70,
        "composure": 70
      },
      "image": "https://cdn.sofifa.net/players/247/019/25_120.png"
    },
    {
      "name": "Falaye Sacko -",
      "number": 77,
      "position": "RB",
      "overall": 72,
      "attributes": {
        "pace": 70,
        "shooting": 70,
        "passing": 70,
        "dribbling": 70,
        "defending": 70,
        "physicality": 70,
        "stamina": 70,
        "awareness": 70,
        "composure": 70
      },
      "image": "https://cdn.sofifa.net/players/230/147/25_120.png"
    },
    {
      "name": "Wahbi Khazri -",
      "number": 10,
      "position": "ST",
      "overall": 72,
      "attributes": {
        "pace": 70,
        "shooting": 70,
        "passing": 70,
        "dribbling": 70,
        "defending": 70,
        "physicality": 70,
        "stamina": 70,
        "awareness": 70,
        "composure": 70
      },
      "image": "https://cdn.sofifa.net/players/194/845/25_120.png"
    },
    {
      "name": "Issiaga Sylla -",
      "number": 3,
      "position": "LB",
      "overall": 72,
      "attributes": {
        "pace": 70,
        "shooting": 70,
        "passing": 70,
        "dribbling": 70,
        "defending": 70,
        "physicality": 70,
        "stamina": 70,
        "awareness": 70,
        "composure": 70
      },
      "image": "https://cdn.sofifa.net/players/212/282/25_120.png"
    },
    {
      "name": "Christopher Jullien -",
      "number": 6,
      "position": "CB",
      "overall": 72,
      "attributes": {
        "pace": 70,
        "shooting": 70,
        "passing": 70,
        "dribbling": 70,
        "defending": 70,
        "physicality": 70,
        "stamina": 70,
        "awareness": 70,
        "composure": 70
      },
      "image": "https://cdn.sofifa.net/players/208/615/25_120.png"
    },
    {
      "name": "Tanguy Coulibaly -",
      "number": 70,
      "position": "LW",
      "overall": 71,
      "attributes": {
        "pace": 70,
        "shooting": 70,
        "passing": 70,
        "dribbling": 70,
        "defending": 70,
        "physicality": 70,
        "stamina": 70,
        "awareness": 70,
        "composure": 70
      },
      "image": "https://cdn.sofifa.net/players/251/401/25_120.png"
    },
    {
      "name": "Enzo Gianni Tchato Mbiayi -",
      "number": 29,
      "position": "RB",
      "overall": 71,
      "attributes": {
        "pace": 70,
        "shooting": 70,
        "passing": 70,
        "dribbling": 70,
        "defending": 70,
        "physicality": 70,
        "stamina": 70,
        "awareness": 70,
        "composure": 70
      },
      "image": "https://cdn.sofifa.net/players/270/518/25_120.png"
    },
    {
      "name": "Lucas Mincarelli Davin -",
      "number": 21,
      "position": "LB",
      "overall": 71,
      "attributes": {
        "pace": 70,
        "shooting": 70,
        "passing": 70,
        "dribbling": 70,
        "defending": 70,
        "physicality": 70,
        "stamina": 70,
        "awareness": 70,
        "composure": 70
      },
      "image": "https://cdn.sofifa.net/players/278/262/25_120.png"
    },
    {
      "name": "Khalil Fayad -",
      "number": 22,
      "position": "CM",
      "overall": 70,
      "attributes": {
        "pace": 70,
        "shooting": 70,
        "passing": 70,
        "dribbling": 70,
        "defending": 70,
        "physicality": 70,
        "stamina": 70,
        "awareness": 70,
        "composure": 70
      },
      "image": "https://cdn.sofifa.net/players/271/306/25_120.png"
    },
    {
      "name": "Théo Sainte-Luce -",
      "number": 17,
      "position": "LB",
      "overall": 69,
      "attributes": {
        "pace": 70,
        "shooting": 70,
        "passing": 70,
        "dribbling": 70,
        "defending": 70,
        "physicality": 70,
        "stamina": 70,
        "awareness": 70,
        "composure": 70
      },
      "image": "https://cdn.sofifa.net/players/241/157/25_120.png"
    },
    {
      "name": "Nikola Maksimović -",
      "number": 52,
      "position": "CB",
      "overall": 69,
      "attributes": {
        "pace": 70,
        "shooting": 70,
        "passing": 70,
        "dribbling": 70,
        "defending": 70,
        "physicality": 70,
        "stamina": 70,
        "awareness": 70,
        "composure": 70
      },
      "image": "https://cdn.sofifa.net/players/215/466/25_120.png"
    },
    {
      "name": "Rabby Nzingoula -",
      "number": 19,
      "position": "CDM",
      "overall": 67,
      "attributes": {
        "pace": 70,
        "shooting": 70,
        "passing": 70,
        "dribbling": 70,
        "defending": 70,
        "physicality": 70,
        "stamina": 70,
        "awareness": 70,
        "composure": 70
      },
      "image": "https://cdn.sofifa.net/players/070/768/25_120.png"
    },
    {
      "name": "Yaël Mouanga Boudzoumou -",
      "number": 47,
      "position": "CB",
      "overall": 63,
      "attributes": {
        "pace": 70,
        "shooting": 70,
        "passing": 70,
        "dribbling": 70,
        "defending": 70,
        "physicality": 70,
        "stamina": 70,
        "awareness": 70,
        "composure": 70
      },
      "image": "https://cdn.sofifa.net/players/072/254/25_120.png"
    },
    {
      "name": "Yanis Ali Issoufou -",
      "number": 39,
      "position": "RW",
      "overall": 62,
      "attributes": {
        "pace": 70,
        "shooting": 70,
        "passing": 70,
        "dribbling": 70,
        "defending": 70,
        "physicality": 70,
        "stamina": 70,
        "awareness": 70,
        "composure": 70
      },
      "image": "https://cdn.sofifa.net/players/278/571/25_120.png"
    },
    {
      "name": "Nicolas Pays -",
      "number": 18,
      "position": "CAM",
      "overall": 62,
      "attributes": {
        "pace": 70,
        "shooting": 70,
        "passing": 70,
        "dribbling": 70,
        "defending": 70,
        "physicality": 70,
        "stamina": 70,
        "awareness": 70,
        "composure": 70
      },
      "image": "https://cdn.sofifa.net/players/076/888/25_120.png"
    }
  ]
}