{
  "name": "France",
  "type": "nation",
  "logo": "https://cdn.sofifa.net/meta/team/18647/30.png",
  "players": [
    {
      "name": "Kylian Mbappé Lottin -",
      "number": 10,
      "position": "ST",
      "overall": 90,
      "attributes": {
        "pace": 70,
        "shooting": 70,
        "passing": 70,
        "dribbling": 70,
        "defending": 70,
        "physicality": 70,
        "stamina": 70,
        "awareness": 70,
        "composure": 70
      },
      "image": "https://cdn.sofifa.net/players/231/747/25_120.png"
    },
    {
      "name": "William Alain André Gabriel Saliba -",
      "number": 17,
      "position": "CB",
      "overall": 87,
      "attributes": {
        "pace": 70,
        "shooting": 70,
        "passing": 70,
        "dribbling": 70,
        "defending": 70,
        "physicality": 70,
        "stamina": 70,
        "awareness": 70,
        "composure": 70
      },
      "image": "https://cdn.sofifa.net/players/243/715/25_120.png"
    },
    {
      "name": "Masour Ousmane Dembélé -",
      "number": 7,
      "position": "RW",
      "overall": 87,
      "attributes": {
        "pace": 70,
        "shooting": 70,
        "passing": 70,
        "dribbling": 70,
        "defending": 70,
        "physicality": 70,
        "stamina": 70,
        "awareness": 70,
        "composure": 70
      },
      "image": "https://cdn.sofifa.net/players/231/443/25_120.png"
    },
    {
      "name": "Mike Peterson Maignan -",
      "number": 16,
      "position": "GK",
      "overall": 87,
      "attributes": {
        "pace": 70,
        "defending": 70,
        "passing": 70,
        "dribbling": 70,
        "physicality": 70,
        "stamina": 70,
        "awareness": 70,
        "composure": 70
      },
      "image": "https://cdn.sofifa.net/players/215/698/25_120.png"
    },
    {
      "name": "Jules Olivier Koundé -",
      "number": 5,
      "position": "RB",
      "overall": 86,
      "attributes": {
        "pace": 70,
        "shooting": 70,
        "passing": 70,
        "dribbling": 70,
        "defending": 70,
        "physicality": 70,
        "stamina": 70,
        "awareness": 70,
        "composure": 70
      },
      "image": "https://cdn.sofifa.net/players/241/486/25_120.png"
    },
    {
      "name": "Theo Bernard François Hernández -",
      "number": 22,
      "position": "LB",
      "overall": 86,
      "attributes": {
        "pace": 70,
        "shooting": 70,
        "passing": 70,
        "dribbling": 70,
        "defending": 70,
        "physicality": 70,
        "stamina": 70,
        "awareness": 70,
        "composure": 70
      },
      "image": "https://cdn.sofifa.net/players/232/656/25_120.png"
    },
    {
      "name": "Michael Akpovie Olise -",
      "number": 11,
      "position": "RW",
      "overall": 85,
      "attributes": {
        "pace": 70,
        "shooting": 70,
        "passing": 70,
        "dribbling": 70,
        "defending": 70,
        "physicality": 70,
        "stamina": 70,
        "awareness": 70,
        "composure": 70
      },
      "image": "https://cdn.sofifa.net/players/247/827/25_120.png"
    },
    {
      "name": "Ibrahima Konaté -",
      "number": 15,
      "position": "CB",
      "overall": 85,
      "attributes": {
        "pace": 70,
        "shooting": 70,
        "passing": 70,
        "dribbling": 70,
        "defending": 70,
        "physicality": 70,
        "stamina": 70,
        "awareness": 70,
        "composure": 70
      },
      "image": "https://cdn.sofifa.net/players/237/678/25_120.png"
    },
    {
      "name": "Dayotchanculle Oswald Upamecano -",
      "number": 4,
      "position": "CB",
      "overall": 85,
      "attributes": {
        "pace": 70,
        "shooting": 70,
        "passing": 70,
        "dribbling": 70,
        "defending": 70,
        "physicality": 70,
        "stamina": 70,
        "awareness": 70,
        "composure": 70
      },
      "image": "https://cdn.sofifa.net/players/229/558/25_120.png"
    },
    {
      "name": "N'Golo Kanté -",
      "number": 13,
      "position": "CDM",
      "overall": 85,
      "attributes": {
        "pace": 70,
        "shooting": 70,
        "passing": 70,
        "dribbling": 70,
        "defending": 70,
        "physicality": 70,
        "stamina": 70,
        "awareness": 70,
        "composure": 70
      },
      "image": "https://cdn.sofifa.net/players/215/914/25_120.png"
    },
    {
      "name": "Aurélien Djani Tchouameni -",
      "number": 8,
      "position": "CDM",
      "overall": 84,
      "attributes": {
        "pace": 70,
        "shooting": 70,
        "passing": 70,
        "dribbling": 70,
        "defending": 70,
        "physicality": 70,
        "stamina": 70,
        "awareness": 70,
        "composure": 70
      },
      "image": "https://cdn.sofifa.net/players/241/637/25_120.png"
    },
    {
      "name": "Benjamin Pavard -",
      "number": 2,
      "position": "CB",
      "overall": 84,
      "attributes": {
        "pace": 70,
        "shooting": 70,
        "passing": 70,
        "dribbling": 70,
        "defending": 70,
        "physicality": 70,
        "stamina": 70,
        "awareness": 70,
        "composure": 70
      },
      "image": "https://cdn.sofifa.net/players/226/851/25_120.png"
    },
    {
      "name": "Kingsley Junior Coman -",
      "number": 25,
      "position": "LW",
      "overall": 84,
      "attributes": {
        "pace": 70,
        "shooting": 70,
        "passing": 70,
        "dribbling": 70,
        "defending": 70,
        "physicality": 70,
        "stamina": 70,
        "awareness": 70,
        "composure": 70
      },
      "image": "https://cdn.sofifa.net/players/213/345/25_120.png"
    },
    {
      "name": "Bradley Barcola -",
      "number": 20,
      "position": "LW",
      "overall": 83,
      "attributes": {
        "pace": 70,
        "shooting": 70,
        "passing": 70,
        "dribbling": 70,
        "defending": 70,
        "physicality": 70,
        "stamina": 70,
        "awareness": 70,
        "composure": 70
      },
      "image": "https://cdn.sofifa.net/players/264/652/25_120.png"
    },
    {
      "name": "Eduardo Celmi Camavinga -",
      "number": 6,
      "position": "CM",
      "overall": 83,
      "attributes": {
        "pace": 70,
        "shooting": 70,
        "passing": 70,
        "dribbling": 70,
        "defending": 70,
        "physicality": 70,
        "stamina": 70,
        "awareness": 70,
        "composure": 70
      },
      "image": "https://cdn.sofifa.net/players/248/243/25_120.png"
    },
    {
      "name": "Adrien Rabiot-Provost -",
      "number": 14,
      "position": "CM",
      "overall": 83,
      "attributes": {
        "pace": 70,
        "shooting": 70,
        "passing": 70,
        "dribbling": 70,
        "defending": 70,
        "physicality": 70,
        "stamina": 70,
        "awareness": 70,
        "composure": 70
      },
      "image": "https://cdn.sofifa.net/players/210/008/25_120.png"
    },
    {
      "name": "Lucas Chevalier -",
      "number": 23,
      "position": "GK",
      "overall": 82,
      "attributes": {
        "pace": 70,
        "defending": 70,
        "passing": 70,
        "dribbling": 70,
        "physicality": 70,
        "stamina": 70,
        "awareness": 70,
        "composure": 70
      },
      "image": "https://cdn.sofifa.net/players/251/752/25_120.png"
    },
    {
      "name": "Mattéo Elias Kenzo Guendouzi Olié -",
      "number": 19,
      "position": "CDM",
      "overall": 82,
      "attributes": {
        "pace": 70,
        "shooting": 70,
        "passing": 70,
        "dribbling": 70,
        "defending": 70,
        "physicality": 70,
        "stamina": 70,
        "awareness": 70,
        "composure": 70
      },
      "image": "https://cdn.sofifa.net/players/236/496/25_120.png"
    },
    {
      "name": "Christopher Alan Nkunku -",
      "number": 26,
      "position": "CAM",
      "overall": 82,
      "attributes": {
        "pace": 70,
        "shooting": 70,
        "passing": 70,
        "dribbling": 70,
        "defending": 70,
        "physicality": 70,
        "stamina": 70,
        "awareness": 70,
        "composure": 70
      },
      "image": "https://cdn.sofifa.net/players/232/411/25_120.png"
    },
    {
      "name": "Désiré Doué -",
      "number": 9,
      "position": "LW",
      "overall": 81,
      "attributes": {
        "pace": 70,
        "shooting": 70,
        "passing": 70,
        "dribbling": 70,
        "defending": 70,
        "physicality": 70,
        "stamina": 70,
        "awareness": 70,
        "composure": 70
      },
      "image": "https://cdn.sofifa.net/players/271/421/25_120.png"
    },
    {
      "name": "Randal Kolo Muani -",
      "number": 12,
      "position": "ST",
      "overall": 81,
      "attributes": {
        "pace": 70,
        "shooting": 70,
        "passing": 70,
        "dribbling": 70,
        "defending": 70,
        "physicality": 70,
        "stamina": 70,
        "awareness": 70,
        "composure": 70
      },
      "image": "https://cdn.sofifa.net/players/237/679/25_120.png"
    },
    {
      "name": "Brice Lauriche Samba -",
      "number": 1,
      "position": "GK",
      "overall": 81,
      "attributes": {
        "pace": 70,
        "defending": 70,
        "passing": 70,
        "dribbling": 70,
        "physicality": 70,
        "stamina": 70,
        "awareness": 70,
        "composure": 70
      },
      "image": "https://cdn.sofifa.net/players/204/883/25_120.png"
    },
    {
      "name": "Warren Zaïre-Emery -",
      "number": 18,
      "position": "CM",
      "overall": 80,
      "attributes": {
        "pace": 70,
        "shooting": 70,
        "passing": 70,
        "dribbling": 70,
        "defending": 70,
        "physicality": 70,
        "stamina": 70,
        "awareness": 70,
        "composure": 70
      },
      "image": "https://cdn.sofifa.net/players/270/673/25_120.png"
    }
  ]
}